gravitypy/__init__.py
gravitypy/__main__.py
gravitypy/main.py
gravitypy/button/__init__.py
gravitypy/button/button.py
gravitypy/particle/__init__.py
gravitypy/particle/particle.py
gravitypy/resources/fonts/minecraft_font.ttf
gravitypy-1.2.4.data/data/gravitypy/resources/fonts/minecraft_font.ttf
gravitypy-1.2.4.dist-info/LICENSE
gravitypy-1.2.4.dist-info/METADATA
gravitypy-1.2.4.dist-info/WHEEL
gravitypy-1.2.4.dist-info/entry_points.txt
gravitypy-1.2.4.dist-info/top_level.txt
gravitypy-1.2.4.dist-info/RECORD
