Metadata-Version: 2.1
Name: gravitypy
Version: 1.2.4
Summary: GravityPy
Home-page: https://github.com/WiktorK02/gravityPy
Author: WiktorK02
Author-email: wiktor.kidon@hotmail.com
License: MIT
License-File: LICENSE
Requires-Dist: pygame (==2.3.0)
